{
  "title": "2.5 Seeds",
  "description": "Seeds — every fact from the textbook.",
  "folder": "School/Grade 10/Biology",
  "field": "natural",
  "anki": true,
  "tags": ["biology", "grade10", "plants"],
  "questions": [
    {
      "id": 1,
      "question": "What are the three parts of a seed?",
      "options": ["Seed coat, fruit and flower", "Seed embryo, cotyledon/endosperm and seed coat", "Radicle, plumule and root", "Epicotyl, hypocotyl and cotyledon"],
      "correctAnswer": "Seed embryo, cotyledon/endosperm and seed coat"
    },
    {
      "id": 2,
      "question": "What is the seed additionally covered by in angiosperms?",
      "options": ["The seed coat only", "The fruit", "The cone", "The flower"],
      "correctAnswer": "The fruit"
    },
    {
      "id": 3,
      "question": "Why are angiosperm seeds called covered seeds?",
      "options": ["They have a thick seed coat", "They are additionally covered by the fruit", "They are covered by cones", "They are covered by leaves"],
      "correctAnswer": "They are additionally covered by the fruit"
    },
    {
      "id": 4,
      "question": "What are gymnosperm seeds called because they have nothing except their own seed coat?",
      "options": ["Covered seeds", "Naked seeds", "Protected seeds", "Shelled seeds"],
      "correctAnswer": "Naked seeds"
    },
    {
      "id": 5,
      "question": "What does the seed embryo consist of?",
      "options": ["Cotyledon and endosperm", "Radicle, epicotyl, hypocotyl and plumule", "Seed coat and fruit", "Stem and leaves"],
      "correctAnswer": "Radicle, epicotyl, hypocotyl and plumule"
    },
    {
      "id": 6,
      "question": "What does the radicle develop into?",
      "options": ["Future shoot", "Future root", "Future leaf", "Future flower"],
      "correctAnswer": "Future root"
    },
    {
      "id": 7,
      "question": "What does the plumule develop into?",
      "options": ["Future root", "Future shoot", "Future seed", "Future fruit"],
      "correctAnswer": "Future shoot"
    },
    {
      "id": 8,
      "question": "What is the function of cotyledon and endosperm?",
      "options": ["They form the seed coat", "They are food storing tissues essential for the seed embryo until it forms leaf and starts manufacturing its own food", "They attract pollinators", "They help in seed dispersal"],
      "correctAnswer": "They are food storing tissues essential for the seed embryo until it forms leaf and starts manufacturing its own food"
    },
    {
      "id": 9,
      "question": "How many cotyledons does a dicot seed have?",
      "options": ["One", "Two", "Three", "Many"],
      "correctAnswer": "Two"
    },
    {
      "id": 10,
      "question": "How many cotyledons does a monocot seed have?",
      "options": ["Two", "Three", "One", "None"],
      "correctAnswer": "One"
    },
    {
      "id": 11,
      "question": "How are dicot cotyledons described in terms of food storage?",
      "options": ["Thin and lack food materials", "Fleshy and store food materials", "Absent", "Hard and dry"],
      "correctAnswer": "Fleshy and store food materials"
    },
    {
      "id": 12,
      "question": "How are monocot cotyledons described in terms of food storage?",
      "options": ["Fleshy and store food", "Very thin and lack food materials", "They are absent", "They store large amounts of food"],
      "correctAnswer": "Very thin and lack food materials"
    },
    {
      "id": 13,
      "question": "What is the status of endosperm in dicot seeds?",
      "options": ["Large and well developed", "Absent", "Small", "Scattered"],
      "correctAnswer": "Absent"
    },
    {
      "id": 14,
      "question": "What is the status of endosperm in monocot seeds?",
      "options": ["Absent", "Large and well developed", "Very small", "Present but not developed"],
      "correctAnswer": "Large and well developed"
    },
    {
      "id": 15,
      "question": "What happens to the primary root in monocot seeds?",
      "options": ["It persists throughout life", "It bears many lateral roots", "It is replaced by adventitious fibrous roots", "It grows deep into the soil"],
      "correctAnswer": "It is replaced by adventitious fibrous roots"
    },
    {
      "id": 16,
      "question": "What does the primary root produced from the radicle in dicot seeds do?",
      "options": ["It is replaced by adventitious roots", "It bears many lateral roots", "It dies quickly", "It becomes a fibrous root system"],
      "correctAnswer": "It bears many lateral roots"
    }
  ]
}
